cloud_base_framework/__init__.py
cloud_base_framework/cloud_base_core.py
cloud_base_framework/cloud_base_exception.py
cloud_base_framework/cloud_base_log.py
cloud_base_framework-0.0.5.dist-info/LICENSE
cloud_base_framework-0.0.5.dist-info/WHEEL
cloud_base_framework-0.0.5.dist-info/METADATA
cloud_base_framework-0.0.5.dist-info/RECORD
