Metadata-Version: 2.1
Name: cloud-base-framework
Version: 0.0.5
Summary: 抖店微应用 python 框架
License: MIT
Author: 陈志峰
Author-email: chenzhifeng.777@bytedance.com
Requires-Python: >=3.10,<4.0
Classifier: License :: OSI Approved :: MIT License
Classifier: Programming Language :: Python :: 3
Classifier: Programming Language :: Python :: 3.10
Classifier: Programming Language :: Python :: 3.11
Requires-Dist: flask (>=2.2.2,<3.0.0)
